aiolizzer/__init__.py
aiolizzer/__main__.py
aiolizzer-0.0.1.dist-info/METADATA
aiolizzer-0.0.1.dist-info/WHEEL
aiolizzer-0.0.1.dist-info/licenses/LICENSE
aiolizzer-0.0.1.dist-info/RECORD
