Metadata-Version: 2.1
Name: aiolizzer
Version: 0.0.1
Summary: Это я создал новую очень крутую библиотеку.
Project-URL: Homepage, https://github.com/pypa/sampleproject
Project-URL: Bug Tracker, https://github.com/pypa/sampleproject/issues
Author-email: Sergey Degtyar <degtyar2023@mail.ru>
License-File: LICENSE
Classifier: License :: OSI Approved :: MIT License
Classifier: Operating System :: OS Independent
Classifier: Programming Language :: Python :: 3
Requires-Python: >=3.7
